riverqueue/__init__.py
riverqueue/client.py
riverqueue/driver.py
riverqueue/fnv.py
riverqueue/models.py
riverqueue/drivers/__init__.py
riverqueue/drivers/sqlalchemy/__init__.py
riverqueue/drivers/sqlalchemy/models.py
riverqueue/drivers/sqlalchemy/pg_misc.py
riverqueue/drivers/sqlalchemy/pg_misc.sql
riverqueue/drivers/sqlalchemy/river_job.py
riverqueue/drivers/sqlalchemy/river_job.sql
riverqueue/drivers/sqlalchemy/sqlalchemy_driver.py
riverqueue_py_tract-0.1.0.dist-info/METADATA
riverqueue_py_tract-0.1.0.dist-info/WHEEL
riverqueue_py_tract-0.1.0.dist-info/RECORD
