Metadata-Version: 2.3
Name: riverqueue-py-tract
Version: 0.1.0
Summary: Add your description here
Author-email: Henry Dashwood <henry@buildwithtract.com>
Requires-Python: >=3.8
Requires-Dist: sqlalchemy>=2.0.30
